{
    "Version": "1.2",
    "Data": {
        "Source": "d:\\actionadventure\\actionadventure\\source\\actionadventure\\actionadventure.cpp",
        "ProvidedModule": "",
        "PCH": "d:\\actionadventure\\actionadventure\\intermediate\\build\\win64\\x64\\actionadventureeditor\\development\\unrealed\\sharedpch.unrealed.project.valapi.valexpapi.cpp20.h.pch",
        "Includes": [
            "d:\\actionadventure\\actionadventure\\intermediate\\build\\win64\\x64\\unrealeditor\\development\\actionadventure\\definitions.actionadventure.h",
            "d:\\actionadventure\\actionadventure\\source\\actionadventure\\actionadventure.h"
        ],
        "ImportedModules": [],
        "ImportedHeaderUnits": []
    }
}